MANIFEST.in
README.rst
setup.py
getenclosures/__init__.py
getenclosures/__main__.py
getenclosures/getenclosures.py
getenclosures.egg-info/PKG-INFO
getenclosures.egg-info/SOURCES.txt
getenclosures.egg-info/dependency_links.txt
getenclosures.egg-info/entry_points.txt
getenclosures.egg-info/requires.txt
getenclosures.egg-info/top_level.txt