Metadata-Version: 1.1
Name: getenclosures
Version: 1.0.2
Summary: Gets all enclosure urls from an RSS feed and pipes them to stdout
Home-page: https://github.com/blha303/getenclosures/
Author: Steven Smith
Author-email: stevensmith.ome@gmail.com
License: MIT
Platform: UNKNOWN
Classifier: Development Status :: 4 - Beta
Classifier: License :: OSI Approved :: MIT License
Classifier: Programming Language :: Python :: 3.4
Classifier: Programming Language :: Python :: 3
Classifier: Intended Audience :: End Users/Desktop
Classifier: Intended Audience :: System Administrators
